protoc_gen_validate/__init__.py
protoc_gen_validate/validator.py
protoc_gen_validate-1.2.1.data/data/data/validate.proto
protoc_gen_validate-1.2.1.dist-info/LICENSE
protoc_gen_validate-1.2.1.dist-info/METADATA
protoc_gen_validate-1.2.1.dist-info/WHEEL
protoc_gen_validate-1.2.1.dist-info/top_level.txt
protoc_gen_validate-1.2.1.dist-info/RECORD
